flask_phpbb3/__init__.py
flask_phpbb3/extension.py
flask_phpbb3/sessions.py
flask_phpbb3/backends/__init__.py
flask_phpbb3/backends/base.py
flask_phpbb3/backends/psycopg2.py
Flask_phpBB3-0.2.1.dist-info/AUTHORS
Flask_phpBB3-0.2.1.dist-info/LICENSE
Flask_phpBB3-0.2.1.dist-info/METADATA
Flask_phpBB3-0.2.1.dist-info/WHEEL
Flask_phpBB3-0.2.1.dist-info/pbr.json
Flask_phpBB3-0.2.1.dist-info/top_level.txt
Flask_phpBB3-0.2.1.dist-info/RECORD
