Metadata-Version: 2.1
Name: Flask-phpBB3
Version: 0.2.1
Summary: Connector for Flask with phpBB3 board
Home-page: https://github.com/MasterMind2k/flask-phpbb3
Author: Gregor Kalisnik
Author-email: gregor@kalisnik.si
License: BSD
Platform: UNKNOWN
Classifier: Environment :: Web Environment
Classifier: Intended Audience :: Developers
Classifier: License :: OSI Approved :: BSD License
Classifier: Operating System :: OS Independent
Classifier: Programming Language :: Python
Classifier: Programming Language :: Python :: 2
Classifier: Programming Language :: Python :: 2.7
Classifier: Topic :: Internet :: WWW/HTTP :: Dynamic Content
Classifier: Topic :: Software Development :: Libraries :: Python Modules
Requires-Dist: psycopg2 (>=2.4.5)
Requires-Dist: Flask (>=0.10)
Requires-Dist: typing
